{
    "User.c324711c-2484-41ed-834d-741bfe2bc380": {
        "id": "c324711c-2484-41ed-834d-741bfe2bc380",
        "created_at": "2023-08-10T10:24:01.517721",
        "updated_at": "2023-08-10T10:24:01.517745",
        "email": "airbnb@gmail.com",
        "__class__": "User"
    },
    "BaseModel.e3b861bc-d4d9-4a6a-8d47-b9a2b735264c": {
        "id": "e3b861bc-d4d9-4a6a-8d47-b9a2b735264c",
        "created_at": "2023-08-10T10:27:32.240955",
        "updated_at": "2023-08-10T10:27:32.240969",
        "__class__": "BaseModel"
    },
    "BaseModel.9d512290-522f-4495-9134-43bf46ad426e": {
        "id": "9d512290-522f-4495-9134-43bf46ad426e",
        "created_at": "2023-08-10T10:27:32.241298",
        "updated_at": "2023-08-10T10:27:32.241302",
        "__class__": "BaseModel"
    },
    "BaseModel.be240030-283f-4694-ae9d-4ee9f5bb8d08": {
        "id": "be240030-283f-4694-ae9d-4ee9f5bb8d08",
        "created_at": "2023-08-10T10:27:32.241590",
        "updated_at": "2023-08-10T10:27:32.241599",
        "__class__": "BaseModel"
    },
    "BaseModel.b509391e-5a8e-447a-be12-849bbc4d46ab": {
        "id": "b509391e-5a8e-447a-be12-849bbc4d46ab",
        "created_at": "2023-08-10T10:27:32.242537",
        "updated_at": "2023-08-10T10:27:32.242542",
        "__class__": "BaseModel"
    },
    "BaseModel.714d17d1-f046-41b0-a285-7abacd5a4a29": {
        "id": "714d17d1-f046-41b0-a285-7abacd5a4a29",
        "created_at": "2023-08-10T10:27:32.242784",
        "updated_at": "2023-08-10T10:27:32.242787",
        "__class__": "BaseModel"
    },
    "BaseModel.2904f535-560c-4fd6-9c0c-bf26cba4abfe": {
        "id": "2904f535-560c-4fd6-9c0c-bf26cba4abfe",
        "created_at": "2023-08-10T10:27:32.243663",
        "updated_at": "2023-08-10T10:27:32.243666",
        "__class__": "BaseModel"
    },
    "BaseModel.b576d381-9efb-4ef3-9b39-00df2a334358": {
        "id": "b576d381-9efb-4ef3-9b39-00df2a334358",
        "created_at": "2023-08-10T10:27:32.243941",
        "updated_at": "2023-08-10T10:27:32.243955",
        "__class__": "BaseModel"
    },
    "BaseModel.cb4d0faf-e3b2-48cc-a62f-8ee53cec5602": {
        "id": "cb4d0faf-e3b2-48cc-a62f-8ee53cec5602",
        "created_at": "2023-08-10T10:27:32.245727",
        "updated_at": "2023-08-10T10:27:32.245732",
        "__class__": "BaseModel"
    },
    "User.6ffc13b7-e64b-4c65-ba85-ac866f321d7a": {
        "id": "6ffc13b7-e64b-4c65-ba85-ac866f321d7a",
        "created_at": "2023-08-10T10:27:32.246640",
        "updated_at": "2023-08-10T10:27:32.246661",
        "__class__": "User"
    },
    "User.9d87a1a4-509b-469e-b3ef-d0092b97c101": {
        "id": "9d87a1a4-509b-469e-b3ef-d0092b97c101",
        "created_at": "2023-08-10T10:27:32.247710",
        "updated_at": "2023-08-10T10:27:32.247716",
        "email": "AirBnB@gmail.com",
        "first_name": "AirBnB",
        "password": "AirBnB123",
        "__class__": "User"
    },
    "User.286c173d-8295-456e-88ae-9b85a7038814": {
        "id": "286c173d-8295-456e-88ae-9b85a7038814",
        "created_at": "2023-08-10T10:27:32.248181",
        "updated_at": "2023-08-10T10:27:32.248258",
        "__class__": "User"
    },
    "BaseModel.675247fe-7e3c-4ab1-bee4-36d6c59ad707": {
        "id": "675247fe-7e3c-4ab1-bee4-36d6c59ad707",
        "created_at": "2023-08-10T10:27:56.480138",
        "updated_at": "2023-08-10T10:27:56.480151",
        "__class__": "BaseModel"
    },
    "BaseModel.d7284a04-e6b9-40a0-9a45-848d84e8648b": {
        "id": "d7284a04-e6b9-40a0-9a45-848d84e8648b",
        "created_at": "2023-08-10T10:27:56.480608",
        "updated_at": "2023-08-10T10:27:56.480611",
        "__class__": "BaseModel"
    },
    "BaseModel.b9138160-4511-4a3b-b666-e6c0ca59df73": {
        "id": "b9138160-4511-4a3b-b666-e6c0ca59df73",
        "created_at": "2023-08-10T10:27:56.480991",
        "updated_at": "2023-08-10T10:27:56.481018",
        "__class__": "BaseModel"
    },
    "BaseModel.4050d378-9569-447f-a1f0-776dcfce45e4": {
        "id": "4050d378-9569-447f-a1f0-776dcfce45e4",
        "created_at": "2023-08-10T10:27:56.481577",
        "updated_at": "2023-08-10T10:27:56.481580",
        "__class__": "BaseModel"
    },
    "BaseModel.ff278b8e-906b-49af-9d32-b9a2015e9a81": {
        "id": "ff278b8e-906b-49af-9d32-b9a2015e9a81",
        "created_at": "2023-08-10T10:27:56.481822",
        "updated_at": "2023-08-10T10:27:56.481825",
        "__class__": "BaseModel"
    },
    "BaseModel.83350ba9-e26b-40a4-9c55-5d6b98b75df0": {
        "id": "83350ba9-e26b-40a4-9c55-5d6b98b75df0",
        "created_at": "2023-08-10T10:27:56.482509",
        "updated_at": "2023-08-10T10:27:56.482512",
        "__class__": "BaseModel"
    },
    "BaseModel.c3c31af5-2753-4d99-8416-37a2405d1d8c": {
        "id": "c3c31af5-2753-4d99-8416-37a2405d1d8c",
        "created_at": "2023-08-10T10:27:56.482654",
        "updated_at": "2023-08-10T10:27:56.482663",
        "__class__": "BaseModel"
    },
    "BaseModel.f7dd8398-45dc-4972-8142-8edbcffe126c": {
        "id": "f7dd8398-45dc-4972-8142-8edbcffe126c",
        "created_at": "2023-08-10T10:27:56.484473",
        "updated_at": "2023-08-10T10:27:56.484477",
        "__class__": "BaseModel"
    },
    "User.69f8b56d-a297-477b-851f-6d963985c563": {
        "id": "69f8b56d-a297-477b-851f-6d963985c563",
        "created_at": "2023-08-10T10:27:56.485203",
        "updated_at": "2023-08-10T10:27:56.485245",
        "__class__": "User"
    },
    "BaseModel.f400b55b-10c0-4723-a89d-8a8a272f2101": {
        "id": "f400b55b-10c0-4723-a89d-8a8a272f2101",
        "created_at": "2023-08-10T10:29:29.001561",
        "updated_at": "2023-08-10T10:29:29.001589",
        "__class__": "BaseModel"
    },
    "BaseModel.c22667b9-68c6-40ae-9923-67681790fa63": {
        "id": "c22667b9-68c6-40ae-9923-67681790fa63",
        "created_at": "2023-08-10T10:29:29.002161",
        "updated_at": "2023-08-10T10:29:29.002163",
        "__class__": "BaseModel"
    },
    "BaseModel.107a5740-dd47-4f98-83f8-204693d1b6a9": {
        "id": "107a5740-dd47-4f98-83f8-204693d1b6a9",
        "created_at": "2023-08-10T10:29:29.002391",
        "updated_at": "2023-08-10T10:29:29.002401",
        "__class__": "BaseModel"
    },
    "BaseModel.1f973ed7-6eed-47cd-805f-017607ac7b85": {
        "id": "1f973ed7-6eed-47cd-805f-017607ac7b85",
        "created_at": "2023-08-10T10:29:29.003036",
        "updated_at": "2023-08-10T10:29:29.003052",
        "__class__": "BaseModel"
    },
    "BaseModel.752ecd7d-3d8e-4c5a-8a04-d5b1bd02c0c1": {
        "id": "752ecd7d-3d8e-4c5a-8a04-d5b1bd02c0c1",
        "created_at": "2023-08-10T10:29:29.003231",
        "updated_at": "2023-08-10T10:29:29.003233",
        "__class__": "BaseModel"
    },
    "BaseModel.403a5b7f-5d31-45f6-9152-496813b2917e": {
        "id": "403a5b7f-5d31-45f6-9152-496813b2917e",
        "created_at": "2023-08-10T10:29:29.003912",
        "updated_at": "2023-08-10T10:29:29.003915",
        "__class__": "BaseModel"
    },
    "BaseModel.c82c791a-8c78-41f5-8b48-aeea797a6809": {
        "id": "c82c791a-8c78-41f5-8b48-aeea797a6809",
        "created_at": "2023-08-10T10:29:29.004056",
        "updated_at": "2023-08-10T10:29:29.004097",
        "__class__": "BaseModel"
    },
    "BaseModel.45cde469-0832-4529-85fd-5575e6e17a73": {
        "id": "45cde469-0832-4529-85fd-5575e6e17a73",
        "created_at": "2023-08-10T10:29:29.006360",
        "updated_at": "2023-08-10T10:29:29.006365",
        "__class__": "BaseModel"
    },
    "User.d0245749-a5a4-44c0-9d76-8032f723166b": {
        "id": "d0245749-a5a4-44c0-9d76-8032f723166b",
        "created_at": "2023-08-10T10:29:29.007318",
        "updated_at": "2023-08-10T10:29:29.007335",
        "__class__": "User"
    },
    "BaseModel.6ababcd9-8e67-4477-9a8f-3d6eefde86b8": {
        "id": "6ababcd9-8e67-4477-9a8f-3d6eefde86b8",
        "created_at": "2023-08-10T10:29:42.098733",
        "updated_at": "2023-08-10T10:29:42.098751",
        "__class__": "BaseModel"
    },
    "BaseModel.0d9a30cc-2efe-477f-bbbf-93ae51f52380": {
        "id": "0d9a30cc-2efe-477f-bbbf-93ae51f52380",
        "created_at": "2023-08-10T10:29:42.099840",
        "updated_at": "2023-08-10T10:29:42.099845",
        "__class__": "BaseModel"
    },
    "BaseModel.c7cae4a3-4088-4886-ad5d-ffaac5aaef0a": {
        "id": "c7cae4a3-4088-4886-ad5d-ffaac5aaef0a",
        "created_at": "2023-08-10T10:29:42.100149",
        "updated_at": "2023-08-10T10:29:42.100159",
        "__class__": "BaseModel"
    },
    "BaseModel.fe3bf557-0da0-4590-97af-a66a28cbe9a1": {
        "id": "fe3bf557-0da0-4590-97af-a66a28cbe9a1",
        "created_at": "2023-08-10T10:29:42.102102",
        "updated_at": "2023-08-10T10:29:42.102107",
        "__class__": "BaseModel"
    },
    "BaseModel.ed0267d4-09d9-4d3e-97ee-a609dd142730": {
        "id": "ed0267d4-09d9-4d3e-97ee-a609dd142730",
        "created_at": "2023-08-10T10:29:42.102311",
        "updated_at": "2023-08-10T10:29:42.102314",
        "__class__": "BaseModel"
    },
    "BaseModel.4f310753-ec70-42b0-a43f-039f3c865a80": {
        "id": "4f310753-ec70-42b0-a43f-039f3c865a80",
        "created_at": "2023-08-10T10:29:42.103017",
        "updated_at": "2023-08-10T10:29:42.103021",
        "__class__": "BaseModel"
    },
    "BaseModel.0600e0e4-5c30-4dd2-a899-408703d53d7b": {
        "id": "0600e0e4-5c30-4dd2-a899-408703d53d7b",
        "created_at": "2023-08-10T10:29:42.103144",
        "updated_at": "2023-08-10T10:29:42.103151",
        "__class__": "BaseModel"
    },
    "BaseModel.07632464-6165-44d0-bf5f-b8916a726a42": {
        "id": "07632464-6165-44d0-bf5f-b8916a726a42",
        "created_at": "2023-08-10T10:29:42.106078",
        "updated_at": "2023-08-10T10:29:42.106083",
        "__class__": "BaseModel"
    },
    "User.4adfc068-b8b9-45f2-9c7c-19e8016fe9c9": {
        "id": "4adfc068-b8b9-45f2-9c7c-19e8016fe9c9",
        "created_at": "2023-08-10T10:29:42.107002",
        "updated_at": "2023-08-10T10:29:42.107019",
        "__class__": "User"
    },
    "BaseModel.77ef7a8d-73e7-49d1-88c6-d4df9a3e4140": {
        "id": "77ef7a8d-73e7-49d1-88c6-d4df9a3e4140",
        "created_at": "2023-08-10T10:30:18.053936",
        "updated_at": "2023-08-10T10:30:18.053958",
        "__class__": "BaseModel"
    },
    "BaseModel.2e3fb661-bcd0-4faf-8c06-a48d292d09fa": {
        "id": "2e3fb661-bcd0-4faf-8c06-a48d292d09fa",
        "created_at": "2023-08-10T10:30:18.054747",
        "updated_at": "2023-08-10T10:30:18.054750",
        "__class__": "BaseModel"
    },
    "BaseModel.cc91219c-6e62-41db-add0-c54de2d530a4": {
        "id": "cc91219c-6e62-41db-add0-c54de2d530a4",
        "created_at": "2023-08-10T10:30:18.055049",
        "updated_at": "2023-08-10T10:30:18.055060",
        "__class__": "BaseModel"
    },
    "BaseModel.71d92c60-ae5a-4500-ab1b-7139db93f2f9": {
        "id": "71d92c60-ae5a-4500-ab1b-7139db93f2f9",
        "created_at": "2023-08-10T10:30:18.055810",
        "updated_at": "2023-08-10T10:30:18.055813",
        "__class__": "BaseModel"
    },
    "BaseModel.6d1fec34-1426-4828-abeb-ec25b12d9def": {
        "id": "6d1fec34-1426-4828-abeb-ec25b12d9def",
        "created_at": "2023-08-10T10:30:18.056002",
        "updated_at": "2023-08-10T10:30:18.056004",
        "__class__": "BaseModel"
    },
    "BaseModel.da9f4d82-7e99-46e3-aff1-cfdfcfb1e49d": {
        "id": "da9f4d82-7e99-46e3-aff1-cfdfcfb1e49d",
        "created_at": "2023-08-10T10:30:18.056681",
        "updated_at": "2023-08-10T10:30:18.056685",
        "__class__": "BaseModel"
    },
    "BaseModel.b279d4e0-5c08-437c-9c9a-5b1d5cf2bf68": {
        "id": "b279d4e0-5c08-437c-9c9a-5b1d5cf2bf68",
        "created_at": "2023-08-10T10:30:18.056821",
        "updated_at": "2023-08-10T10:30:18.056832",
        "__class__": "BaseModel"
    },
    "BaseModel.d1ef3405-019e-4d64-a8fb-3abe65e6d48a": {
        "id": "d1ef3405-019e-4d64-a8fb-3abe65e6d48a",
        "created_at": "2023-08-10T10:30:18.060387",
        "updated_at": "2023-08-10T10:30:18.060391",
        "__class__": "BaseModel"
    },
    "User.cedffc7e-8457-4c83-8344-5ffef7dec5bb": {
        "id": "cedffc7e-8457-4c83-8344-5ffef7dec5bb",
        "created_at": "2023-08-10T10:30:18.061327",
        "updated_at": "2023-08-10T10:30:18.061356",
        "__class__": "User"
    },
    "User.c5f5cf0e-3c90-46bb-9060-4885776bd3dd": {
        "id": "c5f5cf0e-3c90-46bb-9060-4885776bd3dd",
        "created_at": "2023-08-10T10:30:18.062693",
        "updated_at": "2023-08-10T10:30:18.062697",
        "email": "AirBnB@gmail.com",
        "first_name": "AirBnB",
        "password": "AirBnB123",
        "__class__": "User"
    },
    "User.990b0b61-e4b9-43a5-ac3c-44c53a0b97d2": {
        "id": "990b0b61-e4b9-43a5-ac3c-44c53a0b97d2",
        "created_at": "2023-08-10T10:30:18.062978",
        "updated_at": "2023-08-10T10:30:18.063016",
        "__class__": "User"
    },
    "BaseModel.5365ef14-83bf-479e-b193-28a90b312721": {
        "id": "5365ef14-83bf-479e-b193-28a90b312721",
        "created_at": "2023-08-10T10:31:10.468928",
        "updated_at": "2023-08-10T10:31:10.468938",
        "__class__": "BaseModel"
    },
    "BaseModel.e51f8e55-78fc-44b4-898c-46149d26b0f5": {
        "id": "e51f8e55-78fc-44b4-898c-46149d26b0f5",
        "created_at": "2023-08-10T10:31:10.469770",
        "updated_at": "2023-08-10T10:31:10.469772",
        "__class__": "BaseModel"
    },
    "BaseModel.c36e1e6b-3eee-4aed-94c8-a727285e5244": {
        "id": "c36e1e6b-3eee-4aed-94c8-a727285e5244",
        "created_at": "2023-08-10T10:31:10.470215",
        "updated_at": "2023-08-10T10:31:10.470223",
        "__class__": "BaseModel"
    },
    "BaseModel.9e765834-b8eb-42f3-ac50-1fa1da4fb338": {
        "id": "9e765834-b8eb-42f3-ac50-1fa1da4fb338",
        "created_at": "2023-08-10T10:31:10.472460",
        "updated_at": "2023-08-10T10:31:10.472493",
        "__class__": "BaseModel"
    },
    "BaseModel.a0a46c5e-6fd6-47c6-997a-44eb5465969d": {
        "id": "a0a46c5e-6fd6-47c6-997a-44eb5465969d",
        "created_at": "2023-08-10T10:31:10.472805",
        "updated_at": "2023-08-10T10:31:10.472811",
        "__class__": "BaseModel"
    },
    "BaseModel.b5d8959f-9cad-4dc8-aae5-8ad9de14b8e0": {
        "id": "b5d8959f-9cad-4dc8-aae5-8ad9de14b8e0",
        "created_at": "2023-08-10T10:31:10.473621",
        "updated_at": "2023-08-10T10:31:10.473624",
        "__class__": "BaseModel"
    },
    "BaseModel.cb6c5ceb-30dc-45bd-a0bb-d5dcb5a9884d": {
        "id": "cb6c5ceb-30dc-45bd-a0bb-d5dcb5a9884d",
        "created_at": "2023-08-10T10:31:10.473750",
        "updated_at": "2023-08-10T10:31:10.473758",
        "__class__": "BaseModel"
    },
    "BaseModel.d8c6fa74-0235-4c8e-a2a3-4fdf337e1d6f": {
        "id": "d8c6fa74-0235-4c8e-a2a3-4fdf337e1d6f",
        "created_at": "2023-08-10T10:31:10.478734",
        "updated_at": "2023-08-10T10:31:10.478739",
        "__class__": "BaseModel"
    },
    "BaseModel.057f8cab-96a1-4427-8530-9d0bbc23c71a": {
        "id": "057f8cab-96a1-4427-8530-9d0bbc23c71a",
        "created_at": "2023-08-10T10:31:21.341154",
        "updated_at": "2023-08-10T10:31:21.341165",
        "__class__": "BaseModel"
    },
    "BaseModel.430422fd-0c6d-49bf-853f-a1011e165278": {
        "id": "430422fd-0c6d-49bf-853f-a1011e165278",
        "created_at": "2023-08-10T10:31:21.342041",
        "updated_at": "2023-08-10T10:31:21.342043",
        "__class__": "BaseModel"
    },
    "BaseModel.761f08ad-0fc1-4523-ba05-9ce1a023e36d": {
        "id": "761f08ad-0fc1-4523-ba05-9ce1a023e36d",
        "created_at": "2023-08-10T10:31:21.342357",
        "updated_at": "2023-08-10T10:31:21.342367",
        "__class__": "BaseModel"
    },
    "BaseModel.9ff13941-5e88-48fe-af3d-d64abc35bd61": {
        "id": "9ff13941-5e88-48fe-af3d-d64abc35bd61",
        "created_at": "2023-08-10T10:31:21.343639",
        "updated_at": "2023-08-10T10:31:21.343642",
        "__class__": "BaseModel"
    },
    "BaseModel.5b69cc41-2b3b-4757-be43-ef17fc557d7d": {
        "id": "5b69cc41-2b3b-4757-be43-ef17fc557d7d",
        "created_at": "2023-08-10T10:31:21.343904",
        "updated_at": "2023-08-10T10:31:21.343906",
        "__class__": "BaseModel"
    },
    "BaseModel.a94c004d-df6f-4b1f-8c22-9028892403fa": {
        "id": "a94c004d-df6f-4b1f-8c22-9028892403fa",
        "created_at": "2023-08-10T10:31:21.344896",
        "updated_at": "2023-08-10T10:31:21.344899",
        "__class__": "BaseModel"
    },
    "BaseModel.7c95ca8e-3703-4f90-b131-36a7a50a4a4f": {
        "id": "7c95ca8e-3703-4f90-b131-36a7a50a4a4f",
        "created_at": "2023-08-10T10:31:21.345038",
        "updated_at": "2023-08-10T10:31:21.345058",
        "__class__": "BaseModel"
    },
    "BaseModel.7cb7c330-2125-439e-ab49-ef3df4b049e9": {
        "id": "7cb7c330-2125-439e-ab49-ef3df4b049e9",
        "created_at": "2023-08-10T10:31:21.352035",
        "updated_at": "2023-08-10T10:31:21.352039",
        "__class__": "BaseModel"
    },
    "User.7b368795-6385-4631-a893-b778d702b2f7": {
        "id": "7b368795-6385-4631-a893-b778d702b2f7",
        "created_at": "2023-08-10T10:31:21.353229",
        "updated_at": "2023-08-10T10:31:21.353255",
        "__class__": "User"
    },
    "User.e189e3b1-957f-48bd-aa3f-53592e2227f7": {
        "id": "e189e3b1-957f-48bd-aa3f-53592e2227f7",
        "created_at": "2023-08-10T10:31:21.354659",
        "updated_at": "2023-08-10T10:31:21.354677",
        "email": "AirBnB@gmail.com",
        "first_name": "AirBnB",
        "password": "AirBnB123",
        "__class__": "User"
    },
    "User.5d2acc42-0014-420e-ba2c-ea5b93af6b94": {
        "id": "5d2acc42-0014-420e-ba2c-ea5b93af6b94",
        "created_at": "2023-08-10T10:31:21.355004",
        "updated_at": "2023-08-10T10:31:21.355091",
        "__class__": "User"
    },
    "BaseModel.0f302dc1-0c8f-4a88-a5eb-f06c2b1388b6": {
        "id": "0f302dc1-0c8f-4a88-a5eb-f06c2b1388b6",
        "created_at": "2023-08-10T10:31:33.048194",
        "updated_at": "2023-08-10T10:31:33.048205",
        "__class__": "BaseModel"
    },
    "BaseModel.220ce6d1-5c12-4218-b424-d9049e9a2fde": {
        "id": "220ce6d1-5c12-4218-b424-d9049e9a2fde",
        "created_at": "2023-08-10T10:31:33.049301",
        "updated_at": "2023-08-10T10:31:33.049304",
        "__class__": "BaseModel"
    },
    "BaseModel.4b0c766b-2329-48c6-a2dd-a292cc0be0e8": {
        "id": "4b0c766b-2329-48c6-a2dd-a292cc0be0e8",
        "created_at": "2023-08-10T10:31:33.049651",
        "updated_at": "2023-08-10T10:31:33.049661",
        "__class__": "BaseModel"
    },
    "BaseModel.4d21e53e-0eb3-4335-85f1-aed2a453bb3e": {
        "id": "4d21e53e-0eb3-4335-85f1-aed2a453bb3e",
        "created_at": "2023-08-10T10:31:33.050965",
        "updated_at": "2023-08-10T10:31:33.051025",
        "__class__": "BaseModel"
    },
    "BaseModel.03e0bdd2-e0ca-4f32-a8e4-d0b99eadc849": {
        "id": "03e0bdd2-e0ca-4f32-a8e4-d0b99eadc849",
        "created_at": "2023-08-10T10:31:33.051224",
        "updated_at": "2023-08-10T10:31:33.051227",
        "__class__": "BaseModel"
    },
    "BaseModel.89ba8ea6-e7c7-4fc7-8e82-d2dc1638c04a": {
        "id": "89ba8ea6-e7c7-4fc7-8e82-d2dc1638c04a",
        "created_at": "2023-08-10T10:31:33.051879",
        "updated_at": "2023-08-10T10:31:33.051882",
        "__class__": "BaseModel"
    },
    "BaseModel.f7b468d6-e469-4a83-8dea-fe13fafc5a71": {
        "id": "f7b468d6-e469-4a83-8dea-fe13fafc5a71",
        "created_at": "2023-08-10T10:31:33.052044",
        "updated_at": "2023-08-10T10:31:33.052054",
        "__class__": "BaseModel"
    },
    "BaseModel.1b7d458d-d436-47fc-9858-7a2f99c09762": {
        "id": "1b7d458d-d436-47fc-9858-7a2f99c09762",
        "created_at": "2023-08-10T10:31:33.059345",
        "updated_at": "2023-08-10T10:31:33.059349",
        "__class__": "BaseModel"
    },
    "User.4736bc54-a84c-4b64-8c82-6ca36b98590d": {
        "id": "4736bc54-a84c-4b64-8c82-6ca36b98590d",
        "created_at": "2023-08-10T10:31:33.060776",
        "updated_at": "2023-08-10T10:31:33.060798",
        "__class__": "User"
    },
    "BaseModel.4bcd3d54-191f-4184-9c2d-23574c6a95ab": {
        "id": "4bcd3d54-191f-4184-9c2d-23574c6a95ab",
        "created_at": "2023-08-10T10:31:51.751376",
        "updated_at": "2023-08-10T10:31:51.751393",
        "__class__": "BaseModel"
    },
    "BaseModel.9f1304ba-1bf7-4a30-9939-2b47cee258b1": {
        "id": "9f1304ba-1bf7-4a30-9939-2b47cee258b1",
        "created_at": "2023-08-10T10:31:51.754622",
        "updated_at": "2023-08-10T10:31:51.754628",
        "__class__": "BaseModel"
    },
    "BaseModel.9d2751fc-8c07-4e7d-b08c-5dee0540a5c0": {
        "id": "9d2751fc-8c07-4e7d-b08c-5dee0540a5c0",
        "created_at": "2023-08-10T10:31:51.755086",
        "updated_at": "2023-08-10T10:31:51.755109",
        "__class__": "BaseModel"
    },
    "BaseModel.6a0348c1-4f1f-408c-8487-0e4d565af6a8": {
        "id": "6a0348c1-4f1f-408c-8487-0e4d565af6a8",
        "created_at": "2023-08-10T10:31:51.756747",
        "updated_at": "2023-08-10T10:31:51.756750",
        "__class__": "BaseModel"
    },
    "BaseModel.a5d21122-6230-4926-b42f-11a1da51776a": {
        "id": "a5d21122-6230-4926-b42f-11a1da51776a",
        "created_at": "2023-08-10T10:31:51.756841",
        "updated_at": "2023-08-10T10:31:51.756843",
        "__class__": "BaseModel"
    },
    "BaseModel.5cac087d-ecdd-4c74-ae86-6c32dedca827": {
        "id": "5cac087d-ecdd-4c74-ae86-6c32dedca827",
        "created_at": "2023-08-10T10:31:51.757560",
        "updated_at": "2023-08-10T10:31:51.757564",
        "__class__": "BaseModel"
    },
    "BaseModel.c9727073-9654-4235-9f42-00d2195670d6": {
        "id": "c9727073-9654-4235-9f42-00d2195670d6",
        "created_at": "2023-08-10T10:31:51.757697",
        "updated_at": "2023-08-10T10:31:51.757703",
        "__class__": "BaseModel"
    },
    "BaseModel.529c267b-cb8f-43c3-a9ad-1a5d86fdf76b": {
        "id": "529c267b-cb8f-43c3-a9ad-1a5d86fdf76b",
        "created_at": "2023-08-10T10:31:51.763244",
        "updated_at": "2023-08-10T10:31:51.763248",
        "__class__": "BaseModel"
    },
    "User.c498f2aa-423e-4818-b085-19640c936ee7": {
        "id": "c498f2aa-423e-4818-b085-19640c936ee7",
        "created_at": "2023-08-10T10:31:51.764759",
        "updated_at": "2023-08-10T10:31:51.764791",
        "__class__": "User"
    },
    "User.78ebc6c1-7b2e-40ea-b5af-1f4e2b2b400b": {
        "id": "78ebc6c1-7b2e-40ea-b5af-1f4e2b2b400b",
        "created_at": "2023-08-10T10:31:51.766465",
        "updated_at": "2023-08-10T10:31:51.766469",
        "email": "AirBnB@gmail.com",
        "first_name": "AirBnB",
        "password": "AirBnB123",
        "__class__": "User"
    },
    "User.59ecda32-eb0a-4c89-b0bb-4bd0f70a4648": {
        "id": "59ecda32-eb0a-4c89-b0bb-4bd0f70a4648",
        "created_at": "2023-08-10T10:31:51.766724",
        "updated_at": "2023-08-10T10:31:51.767516",
        "__class__": "User"
    },
    "BaseModel.1d7017ce-a6b7-4668-9edc-fc6883c6cd51": {
        "id": "1d7017ce-a6b7-4668-9edc-fc6883c6cd51",
        "created_at": "2023-08-10T10:32:00.570112",
        "updated_at": "2023-08-10T10:32:00.570126",
        "__class__": "BaseModel"
    },
    "BaseModel.f0c2e5d2-f2ce-4f39-8e3a-39f8531441c8": {
        "id": "f0c2e5d2-f2ce-4f39-8e3a-39f8531441c8",
        "created_at": "2023-08-10T10:32:00.571638",
        "updated_at": "2023-08-10T10:32:00.571673",
        "__class__": "BaseModel"
    },
    "BaseModel.10dc4e94-d3e3-4445-96d3-31d447a0c9bd": {
        "id": "10dc4e94-d3e3-4445-96d3-31d447a0c9bd",
        "created_at": "2023-08-10T10:32:00.571993",
        "updated_at": "2023-08-10T10:32:00.572005",
        "__class__": "BaseModel"
    },
    "BaseModel.9c144fa9-42f4-46dc-8076-8e9569823d7c": {
        "id": "9c144fa9-42f4-46dc-8076-8e9569823d7c",
        "created_at": "2023-08-10T10:32:00.574541",
        "updated_at": "2023-08-10T10:32:00.574546",
        "__class__": "BaseModel"
    },
    "BaseModel.5c8591df-179b-4d44-b4dd-0eede5f9319a": {
        "id": "5c8591df-179b-4d44-b4dd-0eede5f9319a",
        "created_at": "2023-08-10T10:32:00.574806",
        "updated_at": "2023-08-10T10:32:00.574816",
        "__class__": "BaseModel"
    },
    "BaseModel.eacee50a-7afa-4c5a-823f-3c26c80f0ce5": {
        "id": "eacee50a-7afa-4c5a-823f-3c26c80f0ce5",
        "created_at": "2023-08-10T10:32:00.575949",
        "updated_at": "2023-08-10T10:32:00.575954",
        "__class__": "BaseModel"
    },
    "BaseModel.01aceacf-21c7-468a-bc5b-adb428162fae": {
        "id": "01aceacf-21c7-468a-bc5b-adb428162fae",
        "created_at": "2023-08-10T10:32:00.576170",
        "updated_at": "2023-08-10T10:32:00.576183",
        "__class__": "BaseModel"
    },
    "BaseModel.928d7ee9-df83-4e76-b3ea-3350816acf4e": {
        "id": "928d7ee9-df83-4e76-b3ea-3350816acf4e",
        "created_at": "2023-08-10T10:32:00.582703",
        "updated_at": "2023-08-10T10:32:00.582708",
        "__class__": "BaseModel"
    },
    "User.b569f153-84c6-4442-8da8-cfd44176b06e": {
        "id": "b569f153-84c6-4442-8da8-cfd44176b06e",
        "created_at": "2023-08-10T10:32:00.584222",
        "updated_at": "2023-08-10T10:32:00.584295",
        "__class__": "User"
    },
    "User.85efb0c3-efd0-42d3-969a-9b507db06b79": {
        "id": "85efb0c3-efd0-42d3-969a-9b507db06b79",
        "created_at": "2023-08-10T10:32:00.586137",
        "updated_at": "2023-08-10T10:32:00.586141",
        "email": "AirBnB@gmail.com",
        "first_name": "AirBnB",
        "password": "AirBnB123",
        "__class__": "User"
    },
    "User.310c814e-49fa-42ab-b85a-17933f66669d": {
        "id": "310c814e-49fa-42ab-b85a-17933f66669d",
        "created_at": "2023-08-10T10:32:00.586502",
        "updated_at": "2023-08-10T10:32:00.591394",
        "__class__": "User"
    },
    "BaseModel.4318c4b8-8bb6-41cb-8ef2-732be4aef256": {
        "id": "4318c4b8-8bb6-41cb-8ef2-732be4aef256",
        "created_at": "2023-08-10T10:32:09.300682",
        "updated_at": "2023-08-10T10:32:09.300694",
        "__class__": "BaseModel"
    },
    "BaseModel.1397c1d3-e552-4d8d-ad4a-bc030e49ed22": {
        "id": "1397c1d3-e552-4d8d-ad4a-bc030e49ed22",
        "created_at": "2023-08-10T10:32:09.302271",
        "updated_at": "2023-08-10T10:32:09.302275",
        "__class__": "BaseModel"
    },
    "BaseModel.5cb2b7d4-84b9-47ed-a512-1c4a743e7010": {
        "id": "5cb2b7d4-84b9-47ed-a512-1c4a743e7010",
        "created_at": "2023-08-10T10:32:09.302626",
        "updated_at": "2023-08-10T10:32:09.302636",
        "__class__": "BaseModel"
    },
    "BaseModel.8e98468b-441e-4752-98e4-1a4d18a91e81": {
        "id": "8e98468b-441e-4752-98e4-1a4d18a91e81",
        "created_at": "2023-08-10T10:32:09.304756",
        "updated_at": "2023-08-10T10:32:09.304762",
        "__class__": "BaseModel"
    },
    "BaseModel.034ada02-c49e-40b2-88b5-0a26f09a6b9f": {
        "id": "034ada02-c49e-40b2-88b5-0a26f09a6b9f",
        "created_at": "2023-08-10T10:32:09.305176",
        "updated_at": "2023-08-10T10:32:09.305181",
        "__class__": "BaseModel"
    },
    "BaseModel.82ccc5d7-ccee-491d-9350-a539e9007d68": {
        "id": "82ccc5d7-ccee-491d-9350-a539e9007d68",
        "created_at": "2023-08-10T10:32:09.306710",
        "updated_at": "2023-08-10T10:32:09.306716",
        "__class__": "BaseModel"
    },
    "BaseModel.116d1bba-ff89-4ec1-966f-09cf157922b7": {
        "id": "116d1bba-ff89-4ec1-966f-09cf157922b7",
        "created_at": "2023-08-10T10:32:09.306881",
        "updated_at": "2023-08-10T10:32:09.306894",
        "__class__": "BaseModel"
    },
    "BaseModel.6f783cc0-eb23-4ced-a603-ea46d0a3c836": {
        "id": "6f783cc0-eb23-4ced-a603-ea46d0a3c836",
        "created_at": "2023-08-10T10:32:09.313492",
        "updated_at": "2023-08-10T10:32:09.313497",
        "__class__": "BaseModel"
    },
    "User.3958bf68-f844-47d0-b02f-e22be09ce8a6": {
        "id": "3958bf68-f844-47d0-b02f-e22be09ce8a6",
        "created_at": "2023-08-10T10:32:09.315483",
        "updated_at": "2023-08-10T10:32:09.315514",
        "__class__": "User"
    },
    "User.f5080dfb-b59a-46d9-a215-dfa563456952": {
        "id": "f5080dfb-b59a-46d9-a215-dfa563456952",
        "created_at": "2023-08-10T10:32:09.317655",
        "updated_at": "2023-08-10T10:32:09.317659",
        "email": "AirBnB@gmail.com",
        "first_name": "AirBnB",
        "password": "AirBnB123",
        "__class__": "User"
    },
    "User.327de0a4-f870-4515-9a66-9be075475e20": {
        "id": "327de0a4-f870-4515-9a66-9be075475e20",
        "created_at": "2023-08-10T10:32:09.317991",
        "updated_at": "2023-08-10T10:32:09.368412",
        "__class__": "User"
    },
    "BaseModel.14e5f321-7f20-4762-9b55-76d7a9efffe3": {
        "id": "14e5f321-7f20-4762-9b55-76d7a9efffe3",
        "created_at": "2023-08-10T10:32:16.856196",
        "updated_at": "2023-08-10T10:32:16.856208",
        "__class__": "BaseModel"
    },
    "BaseModel.f45820f7-2ac4-4d91-b3fb-859966fb45fc": {
        "id": "f45820f7-2ac4-4d91-b3fb-859966fb45fc",
        "created_at": "2023-08-10T10:32:16.858289",
        "updated_at": "2023-08-10T10:32:16.858294",
        "__class__": "BaseModel"
    },
    "BaseModel.e0d64e2b-21e9-4d36-b187-5f50c4c1f3f8": {
        "id": "e0d64e2b-21e9-4d36-b187-5f50c4c1f3f8",
        "created_at": "2023-08-10T10:32:16.858717",
        "updated_at": "2023-08-10T10:32:16.858741",
        "__class__": "BaseModel"
    },
    "BaseModel.132db27a-615a-4638-8ca5-3184480f21e9": {
        "id": "132db27a-615a-4638-8ca5-3184480f21e9",
        "created_at": "2023-08-10T10:32:16.861559",
        "updated_at": "2023-08-10T10:32:16.861565",
        "__class__": "BaseModel"
    },
    "BaseModel.ed9c6893-019f-47ae-8cd3-f4dd2f1eec80": {
        "id": "ed9c6893-019f-47ae-8cd3-f4dd2f1eec80",
        "created_at": "2023-08-10T10:32:16.861773",
        "updated_at": "2023-08-10T10:32:16.861777",
        "__class__": "BaseModel"
    },
    "BaseModel.0db19468-b139-4a34-87c0-813568e65494": {
        "id": "0db19468-b139-4a34-87c0-813568e65494",
        "created_at": "2023-08-10T10:32:16.862461",
        "updated_at": "2023-08-10T10:32:16.862465",
        "__class__": "BaseModel"
    },
    "BaseModel.e456c123-bdd1-42f3-98cd-8ddcab6d2b61": {
        "id": "e456c123-bdd1-42f3-98cd-8ddcab6d2b61",
        "created_at": "2023-08-10T10:32:16.862670",
        "updated_at": "2023-08-10T10:32:16.862682",
        "__class__": "BaseModel"
    },
    "BaseModel.99d63801-fa73-4c27-b288-d68fd09d2442": {
        "id": "99d63801-fa73-4c27-b288-d68fd09d2442",
        "created_at": "2023-08-10T10:32:16.870003",
        "updated_at": "2023-08-10T10:32:16.870009",
        "__class__": "BaseModel"
    },
    "User.dc2275b5-0c8a-4b58-a056-ebc7e9809bd0": {
        "id": "dc2275b5-0c8a-4b58-a056-ebc7e9809bd0",
        "created_at": "2023-08-10T10:32:16.871710",
        "updated_at": "2023-08-10T10:32:16.871732",
        "__class__": "User"
    },
    "User.b4001cf1-d9da-4d64-a4ed-986da2318383": {
        "id": "b4001cf1-d9da-4d64-a4ed-986da2318383",
        "created_at": "2023-08-10T10:32:16.874011",
        "updated_at": "2023-08-10T10:32:16.874062",
        "email": "AirBnB@gmail.com",
        "first_name": "AirBnB",
        "password": "AirBnB123",
        "__class__": "User"
    },
    "User.085bc20d-4af5-45e2-8328-f4f61a0aa3bf": {
        "id": "085bc20d-4af5-45e2-8328-f4f61a0aa3bf",
        "created_at": "2023-08-10T10:32:16.875296",
        "updated_at": "2023-08-10T10:32:17.347021",
        "__class__": "User"
    },
    "BaseModel.591bc73f-696c-4245-987b-225359af031e": {
        "id": "591bc73f-696c-4245-987b-225359af031e",
        "created_at": "2023-08-10T10:32:30.593190",
        "updated_at": "2023-08-10T10:32:30.593201",
        "__class__": "BaseModel"
    },
    "BaseModel.25c04e16-7ab5-438e-ba24-6d10850c6866": {
        "id": "25c04e16-7ab5-438e-ba24-6d10850c6866",
        "created_at": "2023-08-10T10:32:30.594938",
        "updated_at": "2023-08-10T10:32:30.594943",
        "__class__": "BaseModel"
    },
    "BaseModel.75a83bb5-6b1f-4658-aaab-bf751c71f072": {
        "id": "75a83bb5-6b1f-4658-aaab-bf751c71f072",
        "created_at": "2023-08-10T10:32:30.595261",
        "updated_at": "2023-08-10T10:32:30.595274",
        "__class__": "BaseModel"
    },
    "BaseModel.5df43ce6-5336-439b-9750-1b4f71b787e2": {
        "id": "5df43ce6-5336-439b-9750-1b4f71b787e2",
        "created_at": "2023-08-10T10:32:30.597188",
        "updated_at": "2023-08-10T10:32:30.597193",
        "__class__": "BaseModel"
    },
    "BaseModel.698c69a1-ff22-4f45-8a02-f4d2beab9bea": {
        "id": "698c69a1-ff22-4f45-8a02-f4d2beab9bea",
        "created_at": "2023-08-10T10:32:30.597388",
        "updated_at": "2023-08-10T10:32:30.597391",
        "__class__": "BaseModel"
    },
    "BaseModel.f2abedce-5633-435a-bada-a3439257b6ab": {
        "id": "f2abedce-5633-435a-bada-a3439257b6ab",
        "created_at": "2023-08-10T10:32:30.598026",
        "updated_at": "2023-08-10T10:32:30.598029",
        "__class__": "BaseModel"
    },
    "BaseModel.8217d20b-75c5-42c1-a82f-3f04d0c186ed": {
        "id": "8217d20b-75c5-42c1-a82f-3f04d0c186ed",
        "created_at": "2023-08-10T10:32:30.598207",
        "updated_at": "2023-08-10T10:32:30.598213",
        "__class__": "BaseModel"
    },
    "BaseModel.4e5c544c-c169-480c-b3cd-69282215761e": {
        "id": "4e5c544c-c169-480c-b3cd-69282215761e",
        "created_at": "2023-08-10T10:32:30.608032",
        "updated_at": "2023-08-10T10:32:30.608037",
        "__class__": "BaseModel"
    },
    "User.1b426804-7588-4ee7-b93d-24854aee6c16": {
        "id": "1b426804-7588-4ee7-b93d-24854aee6c16",
        "created_at": "2023-08-10T10:32:30.609955",
        "updated_at": "2023-08-10T10:32:30.609977",
        "__class__": "User"
    },
    "User.1e2cab66-6891-48c6-a7f9-ca7cbc7d17f3": {
        "id": "1e2cab66-6891-48c6-a7f9-ca7cbc7d17f3",
        "created_at": "2023-08-10T10:32:30.612273",
        "updated_at": "2023-08-10T10:32:30.612278",
        "email": "AirBnB@gmail.com",
        "first_name": "AirBnB",
        "password": "AirBnB123",
        "__class__": "User"
    },
    "User.de82ea9b-d7df-4a8d-98f1-1307860a6bcc": {
        "id": "de82ea9b-d7df-4a8d-98f1-1307860a6bcc",
        "created_at": "2023-08-10T10:32:30.612683",
        "updated_at": "2023-08-10T10:32:35.322141",
        "__class__": "User"
    },
    "BaseModel.682dc2a1-1e1f-4ac8-8a40-a76a947efd66": {
        "id": "682dc2a1-1e1f-4ac8-8a40-a76a947efd66",
        "created_at": "2023-08-10T10:33:41.121797",
        "updated_at": "2023-08-10T10:33:41.121810",
        "__class__": "BaseModel"
    },
    "BaseModel.7930bda0-ca20-4467-8df7-f4d3ccabd236": {
        "id": "7930bda0-ca20-4467-8df7-f4d3ccabd236",
        "created_at": "2023-08-10T10:33:41.123635",
        "updated_at": "2023-08-10T10:33:41.123640",
        "__class__": "BaseModel"
    },
    "BaseModel.526e83aa-7c33-4f38-a3e0-49278644cc35": {
        "id": "526e83aa-7c33-4f38-a3e0-49278644cc35",
        "created_at": "2023-08-10T10:33:41.123944",
        "updated_at": "2023-08-10T10:33:41.123956",
        "__class__": "BaseModel"
    },
    "BaseModel.c61a95a8-ff63-43c3-8171-01bc8b3456e8": {
        "id": "c61a95a8-ff63-43c3-8171-01bc8b3456e8",
        "created_at": "2023-08-10T10:33:41.125652",
        "updated_at": "2023-08-10T10:33:41.125657",
        "__class__": "BaseModel"
    },
    "BaseModel.989c31ec-36fc-403f-878d-33daa1d57bde": {
        "id": "989c31ec-36fc-403f-878d-33daa1d57bde",
        "created_at": "2023-08-10T10:33:41.125952",
        "updated_at": "2023-08-10T10:33:41.125959",
        "__class__": "BaseModel"
    },
    "BaseModel.99cd3530-aa25-4f33-83cb-7d122037f404": {
        "id": "99cd3530-aa25-4f33-83cb-7d122037f404",
        "created_at": "2023-08-10T10:33:41.126932",
        "updated_at": "2023-08-10T10:33:41.126936",
        "__class__": "BaseModel"
    },
    "BaseModel.650dbe7b-275a-43e9-9e48-b4cf1e8d3c8d": {
        "id": "650dbe7b-275a-43e9-9e48-b4cf1e8d3c8d",
        "created_at": "2023-08-10T10:33:41.127062",
        "updated_at": "2023-08-10T10:33:41.127068",
        "__class__": "BaseModel"
    },
    "BaseModel.cb8bac35-3153-40b9-8699-8a2fca53ade1": {
        "id": "cb8bac35-3153-40b9-8699-8a2fca53ade1",
        "created_at": "2023-08-10T10:33:41.135649",
        "updated_at": "2023-08-10T10:33:41.135656",
        "__class__": "BaseModel"
    },
    "User.8738b039-5ff3-4038-906c-133ea093c24c": {
        "id": "8738b039-5ff3-4038-906c-133ea093c24c",
        "created_at": "2023-08-10T10:33:41.137828",
        "updated_at": "2023-08-10T10:33:41.137849",
        "__class__": "User"
    },
    "User.ade8d0eb-eec9-4310-83bd-2d86b2c0b4dc": {
        "id": "ade8d0eb-eec9-4310-83bd-2d86b2c0b4dc",
        "created_at": "2023-08-10T10:33:41.140288",
        "updated_at": "2023-08-10T10:33:41.140293",
        "email": "AirBnB@gmail.com",
        "first_name": "AirBnB",
        "password": "AirBnB123",
        "__class__": "User"
    },
    "User.1b50e78a-d447-4d34-89ee-eb8fc87fcba8": {
        "id": "1b50e78a-d447-4d34-89ee-eb8fc87fcba8",
        "created_at": "2023-08-10T10:33:41.140660",
        "updated_at": "2023-08-10T10:46:11.960589",
        "first_name": "besufikad",
        "last_name": "Yilma",
        "password": 436546,
        "__class__": "User"
    },
    "BaseModel.f1c788df-5ee7-4f11-92fc-6256ca044db8": {
        "id": "f1c788df-5ee7-4f11-92fc-6256ca044db8",
        "created_at": "2023-08-10T10:54:01.443027",
        "updated_at": "2023-08-10T10:54:01.443041",
        "__class__": "BaseModel"
    },
    "BaseModel.e15e5b9c-f049-4394-a353-d8ae1251a01b": {
        "id": "e15e5b9c-f049-4394-a353-d8ae1251a01b",
        "created_at": "2023-08-10T10:54:01.445568",
        "updated_at": "2023-08-10T10:54:01.445573",
        "__class__": "BaseModel"
    },
    "BaseModel.218b8726-7c20-4f21-86a1-7804ad280c33": {
        "id": "218b8726-7c20-4f21-86a1-7804ad280c33",
        "created_at": "2023-08-10T10:54:01.446079",
        "updated_at": "2023-08-10T10:54:01.446095",
        "__class__": "BaseModel"
    },
    "BaseModel.21b7d62f-0806-4241-a508-32ddb12a365e": {
        "id": "21b7d62f-0806-4241-a508-32ddb12a365e",
        "created_at": "2023-08-10T10:54:01.449383",
        "updated_at": "2023-08-10T10:54:01.449390",
        "__class__": "BaseModel"
    },
    "BaseModel.93710bc0-e9be-4817-98d8-2e896169f0e3": {
        "id": "93710bc0-e9be-4817-98d8-2e896169f0e3",
        "created_at": "2023-08-10T10:54:01.449726",
        "updated_at": "2023-08-10T10:54:01.449733",
        "__class__": "BaseModel"
    },
    "BaseModel.c1a99beb-e9a8-4cb7-9b72-3a4952ac44bb": {
        "id": "c1a99beb-e9a8-4cb7-9b72-3a4952ac44bb",
        "created_at": "2023-08-10T10:54:01.450588",
        "updated_at": "2023-08-10T10:54:01.450592",
        "__class__": "BaseModel"
    },
    "User.3c2edca7-ad54-4683-bada-68f134727af0": {
        "id": "3c2edca7-ad54-4683-bada-68f134727af0",
        "created_at": "2023-08-10T10:54:01.450610",
        "updated_at": "2023-08-10T10:54:01.450611",
        "__class__": "User"
    },
    "BaseModel.01d35b48-9c7e-44e4-9aeb-0a6d064ece7a": {
        "id": "01d35b48-9c7e-44e4-9aeb-0a6d064ece7a",
        "created_at": "2023-08-10T10:54:01.450777",
        "updated_at": "2023-08-10T10:54:01.450783",
        "__class__": "BaseModel"
    },
    "BaseModel.a092de05-ccd7-4ba0-926c-3d417a2f50ea": {
        "id": "a092de05-ccd7-4ba0-926c-3d417a2f50ea",
        "created_at": "2023-08-10T10:54:01.458968",
        "updated_at": "2023-08-10T10:54:01.458972",
        "__class__": "BaseModel"
    },
    "User.7bad997f-af60-4f59-b28e-63709baaf68b": {
        "id": "7bad997f-af60-4f59-b28e-63709baaf68b",
        "created_at": "2023-08-10T10:54:01.461455",
        "updated_at": "2023-08-10T10:54:01.461482",
        "__class__": "User"
    },
    "BaseModel.c5938279-7d7e-4937-a118-0d8b58dfdfea": {
        "id": "c5938279-7d7e-4937-a118-0d8b58dfdfea",
        "created_at": "2023-08-10T10:54:52.505602",
        "updated_at": "2023-08-10T10:54:52.505615",
        "__class__": "BaseModel"
    },
    "BaseModel.5feb6787-e411-4905-901f-6ab93b90059d": {
        "id": "5feb6787-e411-4905-901f-6ab93b90059d",
        "created_at": "2023-08-10T10:54:52.507518",
        "updated_at": "2023-08-10T10:54:52.507521",
        "__class__": "BaseModel"
    },
    "BaseModel.3eb9e8e8-7366-4a76-9551-b7acddbf1ff2": {
        "id": "3eb9e8e8-7366-4a76-9551-b7acddbf1ff2",
        "created_at": "2023-08-10T10:54:52.507761",
        "updated_at": "2023-08-10T10:54:52.507774",
        "__class__": "BaseModel"
    },
    "BaseModel.b62acb48-aa43-412b-ba0b-21ea8713a9d6": {
        "id": "b62acb48-aa43-412b-ba0b-21ea8713a9d6",
        "created_at": "2023-08-10T10:54:52.509742",
        "updated_at": "2023-08-10T10:54:52.509745",
        "__class__": "BaseModel"
    },
    "BaseModel.c94b6dcd-1820-4e73-9444-95ac9c1b168a": {
        "id": "c94b6dcd-1820-4e73-9444-95ac9c1b168a",
        "created_at": "2023-08-10T10:54:52.509885",
        "updated_at": "2023-08-10T10:54:52.509888",
        "__class__": "BaseModel"
    },
    "BaseModel.0f25e49a-ece7-47ea-993c-5fe2c679e71d": {
        "id": "0f25e49a-ece7-47ea-993c-5fe2c679e71d",
        "created_at": "2023-08-10T10:54:52.510593",
        "updated_at": "2023-08-10T10:54:52.510596",
        "__class__": "BaseModel"
    },
    "User.1ddb4d5d-2318-4006-9976-e6fef532001c": {
        "id": "1ddb4d5d-2318-4006-9976-e6fef532001c",
        "created_at": "2023-08-10T10:54:52.510621",
        "updated_at": "2023-08-10T10:54:52.510623",
        "__class__": "User"
    },
    "BaseModel.44d9de05-2f09-4c9a-81d7-ddaf634b2e9d": {
        "id": "44d9de05-2f09-4c9a-81d7-ddaf634b2e9d",
        "created_at": "2023-08-10T10:54:52.510753",
        "updated_at": "2023-08-10T10:54:52.510759",
        "__class__": "BaseModel"
    },
    "BaseModel.00966679-5055-4c11-b2b7-2dfd557d7e92": {
        "id": "00966679-5055-4c11-b2b7-2dfd557d7e92",
        "created_at": "2023-08-10T10:54:52.520267",
        "updated_at": "2023-08-10T10:54:52.520273",
        "__class__": "BaseModel"
    },
    "User.215043f3-5571-45ee-b159-e51915e50fa4": {
        "id": "215043f3-5571-45ee-b159-e51915e50fa4",
        "created_at": "2023-08-10T10:54:52.522391",
        "updated_at": "2023-08-10T10:54:52.522414",
        "__class__": "User"
    },
    "User.443baf0a-ad90-43c9-8a29-57eea0f35f0d": {
        "id": "443baf0a-ad90-43c9-8a29-57eea0f35f0d",
        "created_at": "2023-08-10T10:54:52.525092",
        "updated_at": "2023-08-10T10:54:52.525096",
        "email": "AirBnB@gmail.com",
        "first_name": "AirBnB",
        "password": "AirBnB123",
        "__class__": "User"
    },
    "User.65eb0a58-34d8-47af-9198-1faf94e066f4": {
        "id": "65eb0a58-34d8-47af-9198-1faf94e066f4",
        "created_at": "2023-08-10T10:54:52.525416",
        "updated_at": "2023-08-10T10:54:52.525453",
        "__class__": "User"
    },
    "BaseModel.2be93712-e29d-4369-95ae-84d92d314b03": {
        "id": "2be93712-e29d-4369-95ae-84d92d314b03",
        "created_at": "2023-08-10T10:55:17.597498",
        "updated_at": "2023-08-10T10:55:17.597511",
        "__class__": "BaseModel"
    },
    "BaseModel.fea9a90f-41e3-473a-b7de-b49b561ceb10": {
        "id": "fea9a90f-41e3-473a-b7de-b49b561ceb10",
        "created_at": "2023-08-10T10:55:17.600445",
        "updated_at": "2023-08-10T10:55:17.600452",
        "__class__": "BaseModel"
    },
    "BaseModel.e4b150a9-547a-4c41-b227-ca42e151afd6": {
        "id": "e4b150a9-547a-4c41-b227-ca42e151afd6",
        "created_at": "2023-08-10T10:55:17.600796",
        "updated_at": "2023-08-10T10:55:17.600803",
        "__class__": "BaseModel"
    },
    "BaseModel.a7381b15-113a-45bc-8d40-2524db329cf7": {
        "id": "a7381b15-113a-45bc-8d40-2524db329cf7",
        "created_at": "2023-08-10T10:55:17.602899",
        "updated_at": "2023-08-10T10:55:17.602902",
        "__class__": "BaseModel"
    },
    "BaseModel.6a87e0df-95d9-425e-bfb7-1ef78a956bf3": {
        "id": "6a87e0df-95d9-425e-bfb7-1ef78a956bf3",
        "created_at": "2023-08-10T10:55:17.603235",
        "updated_at": "2023-08-10T10:55:17.603252",
        "__class__": "BaseModel"
    },
    "BaseModel.30091ae4-dfc9-4472-a33e-f1e65ce39b4b": {
        "id": "30091ae4-dfc9-4472-a33e-f1e65ce39b4b",
        "created_at": "2023-08-10T10:55:17.604345",
        "updated_at": "2023-08-10T10:55:17.604348",
        "__class__": "BaseModel"
    },
    "User.997b47cf-5cff-4b25-a6bd-63b746975e92": {
        "id": "997b47cf-5cff-4b25-a6bd-63b746975e92",
        "created_at": "2023-08-10T10:55:17.604362",
        "updated_at": "2023-08-10T10:55:17.604363",
        "__class__": "User"
    },
    "BaseModel.c261c19f-4355-4874-91c5-ae2e7b98c3a3": {
        "id": "c261c19f-4355-4874-91c5-ae2e7b98c3a3",
        "created_at": "2023-08-10T10:55:17.604705",
        "updated_at": "2023-08-10T10:55:17.604719",
        "__class__": "BaseModel"
    },
    "BaseModel.d908ea27-64e3-4eaf-99bc-3c3d1b4d5c69": {
        "id": "d908ea27-64e3-4eaf-99bc-3c3d1b4d5c69",
        "created_at": "2023-08-10T10:55:17.614918",
        "updated_at": "2023-08-10T10:55:17.614923",
        "__class__": "BaseModel"
    },
    "User.e2d54e27-eb30-4bfd-9b27-778e566e2140": {
        "id": "e2d54e27-eb30-4bfd-9b27-778e566e2140",
        "created_at": "2023-08-10T10:55:17.617221",
        "updated_at": "2023-08-10T10:55:17.617243",
        "__class__": "User"
    },
    "User.0e1a706e-05ce-4b6b-b290-8b98f74f26d1": {
        "id": "0e1a706e-05ce-4b6b-b290-8b98f74f26d1",
        "created_at": "2023-08-10T10:55:17.620108",
        "updated_at": "2023-08-10T10:55:17.620113",
        "email": "AirBnB@gmail.com",
        "first_name": "AirBnB",
        "password": "AirBnB123",
        "__class__": "User"
    },
    "User.235bb7d7-d86f-4ba9-a073-a493e684dfd3": {
        "id": "235bb7d7-d86f-4ba9-a073-a493e684dfd3",
        "created_at": "2023-08-10T10:55:17.620432",
        "updated_at": "2023-08-10T10:55:17.620439",
        "__class__": "User"
    },
    "BaseModel.952c4111-98ec-45e1-adde-e08d207ead25": {
        "id": "952c4111-98ec-45e1-adde-e08d207ead25",
        "created_at": "2023-08-10T10:56:33.438597",
        "updated_at": "2023-08-10T10:56:33.438611",
        "__class__": "BaseModel"
    },
    "BaseModel.4d8979cb-2b4e-4590-85ef-54a64f27486a": {
        "id": "4d8979cb-2b4e-4590-85ef-54a64f27486a",
        "created_at": "2023-08-10T10:56:33.440747",
        "updated_at": "2023-08-10T10:56:33.440750",
        "__class__": "BaseModel"
    },
    "BaseModel.28c96c57-8ae1-4d84-9cb6-49a94c6a83f6": {
        "id": "28c96c57-8ae1-4d84-9cb6-49a94c6a83f6",
        "created_at": "2023-08-10T10:56:33.441100",
        "updated_at": "2023-08-10T10:56:33.441109",
        "__class__": "BaseModel"
    },
    "BaseModel.0564cc71-e5e4-436d-8947-012a96114b3b": {
        "id": "0564cc71-e5e4-436d-8947-012a96114b3b",
        "created_at": "2023-08-10T10:56:33.443854",
        "updated_at": "2023-08-10T10:56:33.443860",
        "__class__": "BaseModel"
    },
    "BaseModel.d09def4d-f03a-4cc0-bd4e-ce2e714fc5d9": {
        "id": "d09def4d-f03a-4cc0-bd4e-ce2e714fc5d9",
        "created_at": "2023-08-10T10:56:33.444142",
        "updated_at": "2023-08-10T10:56:33.444148",
        "__class__": "BaseModel"
    },
    "BaseModel.3456a014-2191-4eaa-8e75-eaa00cecc5fa": {
        "id": "3456a014-2191-4eaa-8e75-eaa00cecc5fa",
        "created_at": "2023-08-10T10:56:33.444981",
        "updated_at": "2023-08-10T10:56:33.444985",
        "__class__": "BaseModel"
    },
    "User.26d4864d-5674-43d2-b72f-4068a936c578": {
        "id": "26d4864d-5674-43d2-b72f-4068a936c578",
        "created_at": "2023-08-10T10:56:33.445002",
        "updated_at": "2023-08-10T10:56:33.445002",
        "__class__": "User"
    },
    "BaseModel.a9f7fb9d-cc81-4162-977b-d24058c7864b": {
        "id": "a9f7fb9d-cc81-4162-977b-d24058c7864b",
        "created_at": "2023-08-10T10:56:33.445211",
        "updated_at": "2023-08-10T10:56:33.445218",
        "__class__": "BaseModel"
    },
    "BaseModel.e4092046-5501-4bd0-a8e4-b549c5214db2": {
        "id": "e4092046-5501-4bd0-a8e4-b549c5214db2",
        "created_at": "2023-08-10T10:56:33.455904",
        "updated_at": "2023-08-10T10:56:33.455909",
        "__class__": "BaseModel"
    },
    "User.72d614c7-c1dc-4bc8-851a-90d95d5ade54": {
        "id": "72d614c7-c1dc-4bc8-851a-90d95d5ade54",
        "created_at": "2023-08-10T10:56:33.455936",
        "updated_at": "2023-08-10T10:56:33.455938",
        "__class__": "User"
    },
    "User.19a204bc-3bd5-4450-8bad-00a31dc7105c": {
        "id": "19a204bc-3bd5-4450-8bad-00a31dc7105c",
        "created_at": "2023-08-10T10:56:33.459330",
        "updated_at": "2023-08-10T10:56:33.459350",
        "__class__": "User"
    },
    "User.9c964826-a3da-41d9-beb4-c575ca5607de": {
        "id": "9c964826-a3da-41d9-beb4-c575ca5607de",
        "created_at": "2023-08-10T10:56:33.461727",
        "updated_at": "2023-08-10T10:56:33.461731",
        "email": "AirBnB@gmail.com",
        "first_name": "AirBnB",
        "password": "AirBnB123",
        "__class__": "User"
    },
    "User.14bad364-9aca-48bb-97ee-c70805dbf53d": {
        "id": "14bad364-9aca-48bb-97ee-c70805dbf53d",
        "created_at": "2023-08-10T10:56:33.462158",
        "updated_at": "2023-08-10T10:56:33.462169",
        "__class__": "User"
    },
    "BaseModel.de85cff9-986b-4c43-bc05-fa77ec3d00f6": {
        "id": "de85cff9-986b-4c43-bc05-fa77ec3d00f6",
        "created_at": "2023-08-10T10:58:22.215213",
        "updated_at": "2023-08-10T10:58:22.215234",
        "__class__": "BaseModel"
    },
    "BaseModel.f0087719-3803-4c1f-894d-caf085e5c2ed": {
        "id": "f0087719-3803-4c1f-894d-caf085e5c2ed",
        "created_at": "2023-08-10T10:58:22.218310",
        "updated_at": "2023-08-10T10:58:22.218317",
        "__class__": "BaseModel"
    },
    "BaseModel.c245b918-9055-4f9c-9c43-c90fd359d249": {
        "id": "c245b918-9055-4f9c-9c43-c90fd359d249",
        "created_at": "2023-08-10T10:58:22.218776",
        "updated_at": "2023-08-10T10:58:22.218785",
        "__class__": "BaseModel"
    },
    "BaseModel.5e8b1b3c-0185-422b-a1ab-a44f2200c20a": {
        "id": "5e8b1b3c-0185-422b-a1ab-a44f2200c20a",
        "created_at": "2023-08-10T10:58:22.221153",
        "updated_at": "2023-08-10T10:58:22.221158",
        "__class__": "BaseModel"
    },
    "BaseModel.1f2349ff-d14a-4a74-8f47-c9cdeb7480c0": {
        "id": "1f2349ff-d14a-4a74-8f47-c9cdeb7480c0",
        "created_at": "2023-08-10T10:58:22.221362",
        "updated_at": "2023-08-10T10:58:22.221365",
        "__class__": "BaseModel"
    },
    "BaseModel.bc61bdca-bdcf-4a81-bc49-adee20ed4700": {
        "id": "bc61bdca-bdcf-4a81-bc49-adee20ed4700",
        "created_at": "2023-08-10T10:58:22.222035",
        "updated_at": "2023-08-10T10:58:22.222040",
        "__class__": "BaseModel"
    },
    "User.e16c7121-c5d3-426e-acb7-8d2280988b68": {
        "id": "e16c7121-c5d3-426e-acb7-8d2280988b68",
        "created_at": "2023-08-10T10:58:22.222065",
        "updated_at": "2023-08-10T10:58:22.222067",
        "__class__": "User"
    },
    "BaseModel.420bd9f5-35bb-4e92-ac9e-a0585fda03b3": {
        "id": "420bd9f5-35bb-4e92-ac9e-a0585fda03b3",
        "created_at": "2023-08-10T10:58:22.222223",
        "updated_at": "2023-08-10T10:58:22.222240",
        "__class__": "BaseModel"
    },
    "User.c7e04c5f-1f6e-453e-ba19-dc75c70e1a51": {
        "id": "c7e04c5f-1f6e-453e-ba19-dc75c70e1a51",
        "created_at": "2023-08-10T10:58:22.222236",
        "updated_at": "2023-08-10T10:58:22.224406",
        "__class__": "User"
    },
    "BaseModel.cb7b04f9-fc1c-45d2-bdd6-45c813fe444d": {
        "id": "cb7b04f9-fc1c-45d2-bdd6-45c813fe444d",
        "created_at": "2023-08-10T10:58:22.243619",
        "updated_at": "2023-08-10T10:58:22.243626",
        "__class__": "BaseModel"
    },
    "User.83bbc638-2e49-4699-8006-e5e3ba7fcfdb": {
        "id": "83bbc638-2e49-4699-8006-e5e3ba7fcfdb",
        "created_at": "2023-08-10T10:58:22.243649",
        "updated_at": "2023-08-10T10:58:22.243651",
        "__class__": "User"
    },
    "User.fd907007-2b2d-4f67-ba9e-b9b44602e8b3": {
        "id": "fd907007-2b2d-4f67-ba9e-b9b44602e8b3",
        "created_at": "2023-08-10T10:58:22.246106",
        "updated_at": "2023-08-10T10:58:22.246133",
        "__class__": "User"
    },
    "User.23a7e62c-b7fd-44de-a246-5f8bff4f1768": {
        "id": "23a7e62c-b7fd-44de-a246-5f8bff4f1768",
        "created_at": "2023-08-10T10:58:22.250722",
        "updated_at": "2023-08-10T10:58:22.250728",
        "email": "AirBnB@gmail.com",
        "first_name": "AirBnB",
        "password": "AirBnB123",
        "__class__": "User"
    },
    "User.ad3a6801-197b-4b7c-b7f9-4fb605ca12df": {
        "id": "ad3a6801-197b-4b7c-b7f9-4fb605ca12df",
        "created_at": "2023-08-10T10:58:22.251120",
        "updated_at": "2023-08-10T10:58:22.251126",
        "__class__": "User"
    },
    "BaseModel.1d5707bd-bc2d-4f98-9665-965d6afc1ed9": {
        "id": "1d5707bd-bc2d-4f98-9665-965d6afc1ed9",
        "created_at": "2023-08-10T10:59:07.188468",
        "updated_at": "2023-08-10T10:59:07.188492",
        "__class__": "BaseModel"
    },
    "BaseModel.8d01b6e7-e1c8-4383-ada9-1f45739a760c": {
        "id": "8d01b6e7-e1c8-4383-ada9-1f45739a760c",
        "created_at": "2023-08-10T10:59:07.192714",
        "updated_at": "2023-08-10T10:59:07.192724",
        "__class__": "BaseModel"
    },
    "BaseModel.8aa02d58-aaeb-4d53-8603-20d44aa70d8b": {
        "id": "8aa02d58-aaeb-4d53-8603-20d44aa70d8b",
        "created_at": "2023-08-10T10:59:07.193027",
        "updated_at": "2023-08-10T10:59:07.193039",
        "__class__": "BaseModel"
    },
    "BaseModel.2c4f56b1-e179-4d77-b0ed-13569caca456": {
        "id": "2c4f56b1-e179-4d77-b0ed-13569caca456",
        "created_at": "2023-08-10T10:59:07.196176",
        "updated_at": "2023-08-10T10:59:07.196181",
        "__class__": "BaseModel"
    },
    "BaseModel.9fe93eef-68c5-43b4-b254-d78c0b2cb475": {
        "id": "9fe93eef-68c5-43b4-b254-d78c0b2cb475",
        "created_at": "2023-08-10T10:59:07.196393",
        "updated_at": "2023-08-10T10:59:07.196395",
        "__class__": "BaseModel"
    },
    "BaseModel.57f102a5-b395-4917-a98c-8b6cc060ef1f": {
        "id": "57f102a5-b395-4917-a98c-8b6cc060ef1f",
        "created_at": "2023-08-10T10:59:07.197160",
        "updated_at": "2023-08-10T10:59:07.197164",
        "__class__": "BaseModel"
    },
    "User.19675f51-db76-4a57-ae47-af5311be49c3": {
        "id": "19675f51-db76-4a57-ae47-af5311be49c3",
        "created_at": "2023-08-10T10:59:07.197191",
        "updated_at": "2023-08-10T10:59:07.197193",
        "__class__": "User"
    },
    "BaseModel.8c1bfda7-6b22-4b10-b2d3-e445abbd43d6": {
        "id": "8c1bfda7-6b22-4b10-b2d3-e445abbd43d6",
        "created_at": "2023-08-10T10:59:07.197317",
        "updated_at": "2023-08-10T10:59:07.197358",
        "__class__": "BaseModel"
    },
    "User.4d83460e-6480-40c9-94db-60130e8c848b": {
        "id": "4d83460e-6480-40c9-94db-60130e8c848b",
        "created_at": "2023-08-10T10:59:07.197344",
        "updated_at": "2023-08-10T10:59:07.202707",
        "__class__": "User"
    },
    "BaseModel.31c808b0-7d55-4ccf-9889-6ad64a997201": {
        "id": "31c808b0-7d55-4ccf-9889-6ad64a997201",
        "created_at": "2023-08-10T10:59:07.254571",
        "updated_at": "2023-08-10T10:59:07.254576",
        "__class__": "BaseModel"
    },
    "User.6a88b1ff-0773-4014-b199-cd2ca114211a": {
        "id": "6a88b1ff-0773-4014-b199-cd2ca114211a",
        "created_at": "2023-08-10T10:59:07.254602",
        "updated_at": "2023-08-10T10:59:07.254604",
        "__class__": "User"
    },
    "User.d3abab0a-d056-4f88-af14-508a37120d1b": {
        "id": "d3abab0a-d056-4f88-af14-508a37120d1b",
        "created_at": "2023-08-10T10:59:07.260223",
        "updated_at": "2023-08-10T10:59:07.260283",
        "__class__": "User"
    },
    "User.debc6b62-687b-4a77-ab4c-031fc2f2baec": {
        "id": "debc6b62-687b-4a77-ab4c-031fc2f2baec",
        "created_at": "2023-08-10T10:59:07.262949",
        "updated_at": "2023-08-10T10:59:07.262955",
        "email": "AirBnB@gmail.com",
        "first_name": "AirBnB",
        "password": "AirBnB123",
        "__class__": "User"
    },
    "User.8dec094c-de05-4ae6-926f-ed0b7985d48f": {
        "id": "8dec094c-de05-4ae6-926f-ed0b7985d48f",
        "created_at": "2023-08-10T10:59:07.263422",
        "updated_at": "2023-08-10T10:59:07.263439",
        "__class__": "User"
    },
    "BaseModel.68256b0d-afc1-4204-8add-7698cf24cfc7": {
        "id": "68256b0d-afc1-4204-8add-7698cf24cfc7",
        "created_at": "2023-08-10T10:59:14.278121",
        "updated_at": "2023-08-10T10:59:14.278133",
        "__class__": "BaseModel"
    },
    "BaseModel.f3e602af-cb81-4b1c-ac98-95cae1bc4d11": {
        "id": "f3e602af-cb81-4b1c-ac98-95cae1bc4d11",
        "created_at": "2023-08-10T10:59:14.281306",
        "updated_at": "2023-08-10T10:59:14.281311",
        "__class__": "BaseModel"
    },
    "BaseModel.1afc1253-8614-4319-95ee-a64a00d0cf88": {
        "id": "1afc1253-8614-4319-95ee-a64a00d0cf88",
        "created_at": "2023-08-10T10:59:14.281851",
        "updated_at": "2023-08-10T10:59:14.281859",
        "__class__": "BaseModel"
    },
    "BaseModel.e09a5178-fd2b-4fa6-9a31-e05227b5bbe7": {
        "id": "e09a5178-fd2b-4fa6-9a31-e05227b5bbe7",
        "created_at": "2023-08-10T10:59:14.285228",
        "updated_at": "2023-08-10T10:59:14.285234",
        "__class__": "BaseModel"
    },
    "BaseModel.fd38fe4b-667b-4578-bc5c-8315fd11ef33": {
        "id": "fd38fe4b-667b-4578-bc5c-8315fd11ef33",
        "created_at": "2023-08-10T10:59:14.285658",
        "updated_at": "2023-08-10T10:59:14.285685",
        "__class__": "BaseModel"
    },
    "BaseModel.7ab2f156-69c0-4571-8769-20021d3e008b": {
        "id": "7ab2f156-69c0-4571-8769-20021d3e008b",
        "created_at": "2023-08-10T10:59:14.287237",
        "updated_at": "2023-08-10T10:59:14.287240",
        "__class__": "BaseModel"
    },
    "User.ca24e1bd-4596-4da8-a3f4-85c7af7eb807": {
        "id": "ca24e1bd-4596-4da8-a3f4-85c7af7eb807",
        "created_at": "2023-08-10T10:59:14.287254",
        "updated_at": "2023-08-10T10:59:14.287255",
        "__class__": "User"
    },
    "BaseModel.31df063f-57d6-4884-b3b2-de2d9e35a844": {
        "id": "31df063f-57d6-4884-b3b2-de2d9e35a844",
        "created_at": "2023-08-10T10:59:14.287554",
        "updated_at": "2023-08-10T10:59:14.287606",
        "__class__": "BaseModel"
    },
    "User.726d6ffb-5abd-47d5-b037-77f44b02376b": {
        "id": "726d6ffb-5abd-47d5-b037-77f44b02376b",
        "created_at": "2023-08-10T10:59:14.287591",
        "updated_at": "2023-08-10T10:59:14.290259",
        "__class__": "User"
    },
    "BaseModel.10b73849-88fc-46cf-b522-421a42379be7": {
        "id": "10b73849-88fc-46cf-b522-421a42379be7",
        "created_at": "2023-08-10T10:59:14.312413",
        "updated_at": "2023-08-10T10:59:14.312419",
        "__class__": "BaseModel"
    },
    "User.65dd1830-3dc0-4065-8984-20d1e575d099": {
        "id": "65dd1830-3dc0-4065-8984-20d1e575d099",
        "created_at": "2023-08-10T10:59:14.312446",
        "updated_at": "2023-08-10T10:59:14.312448",
        "__class__": "User"
    },
    "User.6ee2788a-b452-4981-a9eb-666f2ff8a1e3": {
        "id": "6ee2788a-b452-4981-a9eb-666f2ff8a1e3",
        "created_at": "2023-08-10T10:59:14.315910",
        "updated_at": "2023-08-10T10:59:14.315942",
        "__class__": "User"
    },
    "User.f5d12884-75af-4d0c-bf2e-250ab4f99279": {
        "id": "f5d12884-75af-4d0c-bf2e-250ab4f99279",
        "created_at": "2023-08-10T10:59:14.319692",
        "updated_at": "2023-08-10T10:59:14.319698",
        "email": "AirBnB@gmail.com",
        "first_name": "AirBnB",
        "password": "AirBnB123",
        "__class__": "User"
    },
    "User.0e2f8757-4903-48b9-9df8-f3c0afe08557": {
        "id": "0e2f8757-4903-48b9-9df8-f3c0afe08557",
        "created_at": "2023-08-10T10:59:14.320126",
        "updated_at": "2023-08-10T10:59:14.320148",
        "__class__": "User"
    },
    "BaseModel.dc5931d4-3cb3-410d-b623-1fcb73106523": {
        "id": "dc5931d4-3cb3-410d-b623-1fcb73106523",
        "created_at": "2023-08-10T11:00:52.413658",
        "updated_at": "2023-08-10T11:00:52.413699",
        "__class__": "BaseModel"
    },
    "BaseModel.98b83159-5d02-4f4b-a61e-f200397e956c": {
        "id": "98b83159-5d02-4f4b-a61e-f200397e956c",
        "created_at": "2023-08-10T11:00:52.416959",
        "updated_at": "2023-08-10T11:00:52.416967",
        "__class__": "BaseModel"
    },
    "BaseModel.30b3a172-4eca-4cd2-a15e-4e3abab3aea3": {
        "id": "30b3a172-4eca-4cd2-a15e-4e3abab3aea3",
        "created_at": "2023-08-10T11:00:52.417515",
        "updated_at": "2023-08-10T11:00:52.417528",
        "__class__": "BaseModel"
    },
    "BaseModel.308f024a-6976-44e3-8f9f-3a3c5cf3cabf": {
        "id": "308f024a-6976-44e3-8f9f-3a3c5cf3cabf",
        "created_at": "2023-08-10T11:00:52.420540",
        "updated_at": "2023-08-10T11:00:52.420559",
        "__class__": "BaseModel"
    },
    "BaseModel.25a69da9-b331-4745-ab84-55bb164f9136": {
        "id": "25a69da9-b331-4745-ab84-55bb164f9136",
        "created_at": "2023-08-10T11:00:52.420905",
        "updated_at": "2023-08-10T11:00:52.420908",
        "__class__": "BaseModel"
    },
    "BaseModel.62fb7ac9-cf96-4d78-b13b-4219a6d3925a": {
        "id": "62fb7ac9-cf96-4d78-b13b-4219a6d3925a",
        "created_at": "2023-08-10T11:00:52.422320",
        "updated_at": "2023-08-10T11:00:52.422323",
        "__class__": "BaseModel"
    },
    "User.015bfb23-f085-4909-8d46-4921aaa99efe": {
        "id": "015bfb23-f085-4909-8d46-4921aaa99efe",
        "created_at": "2023-08-10T11:00:52.422338",
        "updated_at": "2023-08-10T11:00:52.422339",
        "__class__": "User"
    },
    "BaseModel.eb3d25bc-8d37-4a32-8485-f6e1d4c570a7": {
        "id": "eb3d25bc-8d37-4a32-8485-f6e1d4c570a7",
        "created_at": "2023-08-10T11:00:52.422636",
        "updated_at": "2023-08-10T11:00:52.422660",
        "__class__": "BaseModel"
    },
    "User.54ee0e34-3c3c-4721-8602-6efc294571e0": {
        "id": "54ee0e34-3c3c-4721-8602-6efc294571e0",
        "created_at": "2023-08-10T11:00:52.422655",
        "updated_at": "2023-08-10T11:00:52.425458",
        "__class__": "User"
    },
    "BaseModel.adc73b35-16d7-4d57-a925-0971d98fe758": {
        "id": "adc73b35-16d7-4d57-a925-0971d98fe758",
        "created_at": "2023-08-10T11:00:52.449806",
        "updated_at": "2023-08-10T11:00:52.449811",
        "__class__": "BaseModel"
    },
    "User.567cd891-e9e6-4fa1-bf25-4d4d853ae7ca": {
        "id": "567cd891-e9e6-4fa1-bf25-4d4d853ae7ca",
        "created_at": "2023-08-10T11:00:52.449833",
        "updated_at": "2023-08-10T11:00:52.449834",
        "__class__": "User"
    },
    "User.ccb72b9b-6daf-47ab-b7a8-270c4056c035": {
        "id": "ccb72b9b-6daf-47ab-b7a8-270c4056c035",
        "created_at": "2023-08-10T11:00:52.453729",
        "updated_at": "2023-08-10T11:00:52.453760",
        "__class__": "User"
    },
    "User.2c85fef7-be79-49d0-8134-41451f28d201": {
        "id": "2c85fef7-be79-49d0-8134-41451f28d201",
        "created_at": "2023-08-10T11:00:52.457743",
        "updated_at": "2023-08-10T11:00:52.457748",
        "email": "AirBnB@gmail.com",
        "first_name": "AirBnB",
        "password": "AirBnB123",
        "__class__": "User"
    },
    "User.d12cb79b-454b-4364-893d-fdeaf59853d7": {
        "id": "d12cb79b-454b-4364-893d-fdeaf59853d7",
        "created_at": "2023-08-10T11:00:52.458905",
        "updated_at": "2023-08-10T11:00:52.458920",
        "__class__": "User"
    }
}